mkdocs_api_autonav/__init__.py
mkdocs_api_autonav/plugin.py
mkdocs_api_autonav/py.typed
mkdocs_api_autonav-0.4.0.dist-info/METADATA
mkdocs_api_autonav-0.4.0.dist-info/WHEEL
mkdocs_api_autonav-0.4.0.dist-info/entry_points.txt
mkdocs_api_autonav-0.4.0.dist-info/licenses/LICENSE
mkdocs_api_autonav-0.4.0.dist-info/RECORD
