Metadata-Version: 2.4
Name: mkdocs-api-autonav
Version: 0.4.0
Summary: Autogenerate API docs with mkdocstrings, including nav
Project-URL: homepage, https://github.com/tlambert03/mkdocs-api-autonav
Project-URL: repository, https://github.com/tlambert03/mkdocs-api-autonav
Author-email: Talley Lambert <talley.lambert@gmail.com>
License: BSD-3-Clause
License-File: LICENSE
Classifier: Development Status :: 4 - Beta
Classifier: License :: OSI Approved :: BSD License
Classifier: Programming Language :: Python :: 3
Classifier: Programming Language :: Python :: 3.9
Classifier: Programming Language :: Python :: 3.10
Classifier: Programming Language :: Python :: 3.11
Classifier: Programming Language :: Python :: 3.12
Classifier: Programming Language :: Python :: 3.13
Classifier: Typing :: Typed
Requires-Python: >=3.9
Requires-Dist: mkdocs>=1.6
Requires-Dist: mkdocstrings-python>=1.11.0
Requires-Dist: pyyaml>=5
